sova_sdk/__init__.py
sova_sdk/auth.py
sova_sdk/block_engine.py
sova_sdk/client.py
sova_sdk/constants.py
sova_sdk/searcher.py
sova_sdk/generated/__init__.py
sova_sdk/generated/auth_pb2.py
sova_sdk/generated/auth_pb2.pyi
sova_sdk/generated/auth_pb2_grpc.py
sova_sdk/generated/block_engine_pb2.py
sova_sdk/generated/block_engine_pb2.pyi
sova_sdk/generated/block_engine_pb2_grpc.py
sova_sdk/generated/dto_pb2.py
sova_sdk/generated/dto_pb2.pyi
sova_sdk/generated/dto_pb2_grpc.py
sova_sdk/generated/searcher_pb2.py
sova_sdk/generated/searcher_pb2.pyi
sova_sdk/generated/searcher_pb2_grpc.py
sova_sdk-0.1.1.dist-info/METADATA
sova_sdk-0.1.1.dist-info/WHEEL
sova_sdk-0.1.1.dist-info/top_level.txt
sova_sdk-0.1.1.dist-info/RECORD
