Metadata-Version: 2.4
Name: sova-sdk
Version: 0.1.1
Summary: Python SDK for Sova Network MEV infrastructure on TON blockchain
Author: Sova Network
License-Expression: MIT
Project-URL: Homepage, https://github.com/sova-network/sova-sdk-python
Project-URL: Repository, https://github.com/sova-network/sova-sdk-python
Requires-Python: >=3.8
Requires-Dist: grpcio>=1.60.0
Requires-Dist: grpcio-tools>=1.60.0
Requires-Dist: protobuf>=4.25.0
Requires-Dist: pynacl>=1.5.0
